rimo_utils/__init__.py
rimo_utils/_杂物.py
rimo_utils/cache.py
rimo_utils/cv0.py
rimo_utils/matrix.py
rimo_utils/sto.py
rimo_utils/计时.py
rimo_utils/cef_tools/fake_wx.py
rimo_utils/cef_tools/qtcef.py
rimo_utils/cef_tools/vue_ob.py
rimo_utils/cef_tools/wxcef.py
rimo_utils-1.7.0.dist-info/METADATA
rimo_utils-1.7.0.dist-info/WHEEL
rimo_utils-1.7.0.dist-info/top_level.txt
rimo_utils-1.7.0.dist-info/RECORD
