Metadata-Version: 2.1
Name: rimo-utils
Version: 1.7.0
Summary: RimoChan util.
Home-page: https://github.com/RimoChan/rimo_utils
Author: RimoChan
Author-email: the@librian.net
License: UNKNOWN
Platform: UNKNOWN
Classifier: Programming Language :: Python :: 3
Classifier: Operating System :: OS Independent
Requires-Python: >=3.6
Requires-Dist: chardet (==3.0.4)
